namable_classify/__init__.py
namable_classify/__main__.py
namable_classify/_modidx.py
namable_classify/core.py
namable_classify/metrics.py
namable_classify/utils.py
namable_classify/auto/__init__.py
namable_classify/auto/experiment.py
namable_classify/auto/run.py
namable_classify/auto/examples/__init__.py
namable_classify/auto/examples/full_finetune.py
namable_classify/data/__init__.py
namable_classify/data/transforms.py
namable_classify-0.0.2.dist-info/LICENSE
namable_classify-0.0.2.dist-info/METADATA
namable_classify-0.0.2.dist-info/WHEEL
namable_classify-0.0.2.dist-info/entry_points.txt
namable_classify-0.0.2.dist-info/top_level.txt
namable_classify-0.0.2.dist-info/RECORD
