Metadata-Version: 2.1
Name: namable_classify
Version: 0.0.2
Home-page: https://github.com/2catycm/NamableClassify
Author: 叶璨铭
Author-email: ycm24@mails.tsinghua.edu.cn
License: Apache Software License 2.0
Keywords: nbdev jupyter notebook python
Classifier: Development Status :: 4 - Beta
Classifier: Intended Audience :: Developers
Classifier: Natural Language :: English
Classifier: Programming Language :: Python :: 3.7
Classifier: Programming Language :: Python :: 3.8
Classifier: Programming Language :: Python :: 3.9
Classifier: Programming Language :: Python :: 3.10
Classifier: Programming Language :: Python :: 3.11
Classifier: Programming Language :: Python :: 3.12
Classifier: License :: OSI Approved :: Apache Software License
Requires-Python: >=3.7
License-File: LICENSE
Requires-Dist: fastcore
Requires-Dist: decorator
Requires-Dist: pydantic
Requires-Dist: loguru
Requires-Dist: bigmodelvis
Requires-Dist: richuru
Requires-Dist: transformers
Requires-Dist: scikit-learn
Requires-Dist: torch
Requires-Dist: torchvision
Requires-Dist: numpy
Requires-Dist: lightning
Requires-Dist: optuna
Requires-Dist: optuna-integration
Requires-Dist: optuna-dashboard
Requires-Dist: plotly
Requires-Dist: psycopg2-binary
Requires-Dist: sqlalchemy
Requires-Dist: clearml
Requires-Dist: wandb
Requires-Dist: tensorboard
Requires-Dist: mlflow
Requires-Dist: psutil
Requires-Dist: nvgpu
Provides-Extra: dev
Requires-Dist: ipykernel; extra == "dev"
Requires-Dist: twine; extra == "dev"
Requires-Dist: nbdev; extra == "dev"
